django_qsessions-2.1.0.dist-info/licenses/LICENSE.txt
qsessions/__init__.py
qsessions/admin.py
qsessions/apps.py
qsessions/geoip.py
qsessions/middleware.py
qsessions/models.py
qsessions/backends/__init__.py
qsessions/backends/cached_db.py
qsessions/backends/db.py
qsessions/management/__init__.py
qsessions/management/commands/__init__.py
qsessions/management/commands/clearsessions.py
qsessions/management/commands/download_geoip_db.py
qsessions/migrations/0001_initial.py
qsessions/migrations/0002_session_created_at.py
qsessions/migrations/__init__.py
django_qsessions-2.1.0.dist-info/METADATA
django_qsessions-2.1.0.dist-info/WHEEL
django_qsessions-2.1.0.dist-info/top_level.txt
django_qsessions-2.1.0.dist-info/RECORD
